README.md
setup.py
previewgen/__init__.py
previewgen/__main__.py
previewgen/previewer.py
previewgen/previewgenerator.py
previewgen/scanner.py
previewgen.egg-info/PKG-INFO
previewgen.egg-info/SOURCES.txt
previewgen.egg-info/dependency_links.txt
previewgen.egg-info/entry_points.txt
previewgen.egg-info/requires.txt
previewgen.egg-info/top_level.txt