Metadata-Version: 2.1
Name: previewgen
Version: 1.3
Summary: UNKNOWN
Home-page: https://github.com/michalfilippi/PreviewGen
Author: Michal Filippi
Author-email: michal.filippi@gmail.com
License: UNKNOWN
Platform: UNKNOWN
Classifier: Programming Language :: Python :: 3
Classifier: License :: OSI Approved :: MIT License
Classifier: Operating System :: OS Independent
